{
  "sent": [
    {
      "phone": "5571988067626",
      "nome": "LIGIA LIMA FONTANARI JACINTO",
      "agendamentoId": 456815158,
      "dataHoraInicio": "28-04-2026T16:30",
      "messageId": "6442763B53B56BD4E459",
      "status": "sent",
      "turno": "afternoon"
    },
    {
      "phone": "5571991927242",
      "nome": "Suely Dalmondez Castro",
      "agendamentoId": 456765539,
      "dataHoraInicio": "28-04-2026T16:00",
      "messageId": "3EB056DFFA2B028ABC7F18",
      "status": "sent",
      "turno": "afternoon"
    },
    {
      "phone": "5571993652820",
      "nome": "Tainara Selene Japiassu de França",
      "agendamentoId": 448560484,
      "dataHoraInicio": "28-04-2026T17:00",
      "messageId": "3EB0C51DF85CA0750D77C8",
      "status": "sent",
      "turno": "afternoon"
    }
  ]
}